vsm/__init__.py
vsm/spatial.py
vsm/split.py
vsm/structarr.py
vsm/zipfile.py
vsm/corpus/__init__.py
vsm/corpus/base.py
vsm/corpus/util/__init__.py
vsm/corpus/util/corpusbuilders.py
vsm/exceptions/__init__.py
vsm/exceptions/compatibility.py
vsm/extensions/__init__.py
vsm/extensions/editions.py
vsm/extensions/htrc.py
vsm/extensions/inpho.py
vsm/extensions/ldasentences.py
vsm/extensions/multi_k.py
vsm/extensions/trans.py
vsm/extensions/clustering/__init__.py
vsm/extensions/clustering/manifold.py
vsm/extensions/clustering/plotting.py
vsm/extensions/corpusbuilders/__init__.py
vsm/extensions/corpusbuilders/corpusbuilders.py
vsm/extensions/corpusbuilders/corpusstreamers.py
vsm/extensions/corpusbuilders/util.py
vsm/extensions/interop/__init__.py
vsm/extensions/interop/ldac.py
vsm/extensions/interop/mallet.py
vsm/extensions/interop/weka.py
vsm/model/__init__.py
vsm/model/_cgs_update.cpython-36m-darwin.so
vsm/model/base.py
vsm/model/beaglecomposite.py
vsm/model/beaglecontext.py
vsm/model/beagleenvironment.py
vsm/model/beagleorder.py
vsm/model/lda.py
vsm/model/ldacgs.py
vsm/model/ldacgsmulti.py
vsm/model/ldacgsseq.py
vsm/model/ldaexact.py
vsm/model/ldafunctions.py
vsm/model/ldagibbs.py
vsm/model/lsa.py
vsm/model/tf.py
vsm/model/tfidf.py
vsm/viewer/__init__.py
vsm/viewer/beagleviewer.py
vsm/viewer/labeleddata.py
vsm/viewer/ldacgsviewer.py
vsm/viewer/ldagibbsviewer.py
vsm/viewer/lsaviewer.py
vsm/viewer/tfidfviewer.py
vsm/viewer/tfviewer.py
vsm/viewer/types.py
vsm/viewer/wrappers.py
vsm-0.4.15.dist-info/LICENSE.txt
vsm-0.4.15.dist-info/METADATA
vsm-0.4.15.dist-info/WHEEL
vsm-0.4.15.dist-info/dependency_links.txt
vsm-0.4.15.dist-info/top_level.txt
vsm-0.4.15.dist-info/RECORD
